<?xml version="1.0" encoding="utf-8"?>
<Level width ="2">
<Camera x="0" y="2" minWidth="20" maxWidth="30" />
<Birds>
<Bird type="BirdRed"/>
<Bird type="BirdYellow"/>
<Bird type="BirdBlack"/>
<Bird type="BirdBlack"/>
<Bird type="BirdBlack"/>
</Birds>
<Slingshot x="-8" y="-2.5" />
<GameObjects>
<Block type="RectFat" material="ice" x="-2.5498627223" y="-3.285" rotation="0" />
<Block type="RectFat" material="wood" x="-1.2598627223" y="-3.285" rotation="0" />
<Block type="RectFat" material="ice" x="0.0301372777" y="-3.285" rotation="0" />
<Block type="RectFat" material="stone" x="1.3201372777" y="-3.285" rotation="0" />
<Block type="RectFat" material="wood" x="2.6101372777" y="-3.285" rotation="0" />
<Block type="RectBig" material="stone" x="4.6648782286082096" y="-3.39" rotation="0" />
<Block type="RectMedium" material="ice" x="6.5897409509" y="-2.66" rotation="90" />
<Block type="RectMedium" material="ice" x="7.2197409509" y="-2.66" rotation="90" />
<Block type="RectMedium" material="stone" x="8.0497409509" y="-2.66" rotation="90" />
<Block type="RectMedium" material="ice" x="8.6797409509" y="-2.66" rotation="90" />
<Block type="RectFat" material="wood" x="6.9047409509" y="-1.605" rotation="0" />
<Block type="RectFat" material="wood" x="8.3647409509" y="-1.605" rotation="0" />
<Block type="RectMedium" material="ice" x="7.6347409509" y="-1.28" rotation="0" />
<Block type="RectSmall" material="ice" x="7.634740950896476" y="-0.745" rotation="90" />
<Block type="SquareSmall" material="ice" x="3.6069676758" y="-0.1420406153" rotation="0" />
<Block type="SquareSmall" material="ice" x="4.5269676758" y="-0.1420406153" rotation="0" />
<Block type="SquareSmall" material="wood" x="5.4469676758" y="-0.1420406153" rotation="0" />
<Block type="RectFat" material="ice" x="3.6069676758" y="0.4979593847" rotation="90" />
<Block type="RectFat" material="wood" x="4.5269676758" y="0.4979593847" rotation="90" />
<Block type="RectFat" material="wood" x="5.4469676758" y="0.4979593847" rotation="90" />
<Block type="RectBig" material="ice" x="4.5269676758" y="1.0329593847" rotation="0" />
<Block type="SquareSmall" material="stone" x="3.7969676758" y="1.3579593847" rotation="0" />
<Block type="SquareSmall" material="ice" x="4.5269676758" y="1.3579593847" rotation="0" />
<Block type="SquareSmall" material="stone" x="5.2569676758" y="1.3579593847" rotation="0" />
<Block type="RectFat" material="wood" x="3.7969676758" y="1.9979593847" rotation="90" />
<Block type="RectFat" material="wood" x="4.5269676758" y="1.9979593847" rotation="90" />
<Block type="RectFat" material="wood" x="5.2569676758" y="1.9979593847" rotation="90" />
<Block type="RectMedium" material="wood" x="4.526967675843273" y="2.5329593847" rotation="0" />
<Block type="RectFat" material="wood" x="-0.7523215034" y="-0.9768073908" rotation="0" />
<Block type="RectFat" material="ice" x="0.1676784966" y="-0.9768073908" rotation="0" />
<Block type="RectFat" material="wood" x="1.0876784966" y="-0.9768073908" rotation="0" />
<Block type="RectBig" material="ice" x="0.1676784966" y="-0.6518073908" rotation="0" />
<Block type="RectFat" material="ice" x="-0.5623215034" y="-0.1168073908" rotation="90" />
<Block type="RectFat" material="ice" x="0.8976784966" y="-0.1168073908" rotation="90" />
<Block type="RectMedium" material="stone" x="0.1676784965814413" y="0.4181926092" rotation="0" />
<Block type="CircleSmall" material="stone" x="1.603470611" y="-2.845" rotation="0" />
<Block type="Triangle" material="wood" x="-2.5498627223" y="-2.66" rotation="90.0" />
<Block type="TriangleHole" material="ice" x="4.5269676758" y="3.0529593847" rotation="0" />
<Block type="CircleSmall" material="wood" x="7.6347409509" y="-0.095" rotation="0" />
<Block type="TriangleHole" material="stone" x="-0.2531960556" y="-2.66" rotation="0" />
<Block type="Circle" material="stone" x="4.6648782286" y="-2.88" rotation="0" />
<Block type="CircleSmall" material="ice" x="0.7276784966" y="0.7531926092" rotation="0" />
<Block type="Triangle" material="wood" x="0.1676784966" y="-0.1318073908" rotation="90.0" />
<Block type="TriangleHole" material="ice" x="7.0747409509" y="-0.76" rotation="0" />
<Block type="CircleSmall" material="wood" x="1.0368039444" y="-2.845" rotation="0" />
<Block type="CircleSmall" material="ice" x="-0.3923215034" y="0.7531926092" rotation="0" />
<Pig type="BasicSmall" material="" x="-1.2598627223" y="-2.82" rotation="0" />
<Pig type="BasicSmall" material="" x="2.3268039444" y="-2.82" rotation="0" />
<Pig type="BasicSmall" material="" x="2.893470611" y="-2.82" rotation="0" />
<Pig type="BasicSmall" material="" x="3.9782115619" y="-3.03" rotation="0" />
<Pig type="BasicSmall" material="" x="8.1947409509" y="-0.92" rotation="0" />
<Pig type="BasicSmall" material="" x="0.1676784966" y="0.7781926092" rotation="0" />
<Platform type="Platform" material="" x="3.596967675843273" y="-0.6670406153104171" />
<Platform type="Platform" material="" x="4.216967675843273" y="-0.6670406153104171" />
<Platform type="Platform" material="" x="4.8369676758432725" y="-0.6670406153104171" />
<Platform type="Platform" material="" x="5.456967675843273" y="-0.6670406153104171" />
<Platform type="Platform" material="" x="-1.0723215034185587" y="-1.5018073908072582" />
<Platform type="Platform" material="" x="-0.4523215034185587" y="-1.5018073908072582" />
<Platform type="Platform" material="" x="0.1676784965814413" y="-1.5018073908072582" />
<Platform type="Platform" material="" x="0.7876784965814413" y="-1.5018073908072582" />
<Platform type="Platform" material="" x="1.4076784965814413" y="-1.5018073908072582" />
<TNT type="" material="" x="7.6597409509" y="-3.25" rotation="0" />
<TNT type="" material="" x="5.3515448953" y="-3.03" rotation="0" />
</GameObjects>
</Level>
